podge/__init__.py
podge/main.py
podge-0.0.1.dist-info/LICENSE
podge-0.0.1.dist-info/METADATA
podge-0.0.1.dist-info/WHEEL
podge-0.0.1.dist-info/top_level.txt
podge-0.0.1.dist-info/RECORD
